jupytorg/__init__.py
jupytorg/__main__.py
jupytorg/aux.c
jupytorg/aux.h
jupytorg/figures/arch.png
jupytorg/figures/forkjoin.png
jupytorg/figures/numa.png
jupytorg/figures/numa.svg
jupytorg/figures/openmp_logo.png
jupytorg/figures/par_arch.png
jupytorg/figures/par_arch.svg
jupytorg/figures/procs_history.png
jupytorg/figures/rambo.jpg
jupytorg/figures/sched.png
jupytorg/figures/sched.svg
jupytorg/figures/scheds.png
jupytorg/newcourse.ipynb
jupytorg/newcourse.json
jupytorg/newcourse.org
jupytorg/out2.html
jupytorg/out2.json
jupytorg/test
jupytorg/test.c
jupytorg-0.2.5.dist-info/METADATA
jupytorg-0.2.5.dist-info/WHEEL
jupytorg-0.2.5.dist-info/entry_points.txt
jupytorg-0.2.5.dist-info/RECORD
