Metadata-Version: 2.1
Name: jupytorg
Version: 0.2.5
Summary: Convert org-mode files to Jupyter Notebooks
Home-page: https://git.inpt.fr/net7/jupytorg
Author: Nathan Auchère
Author-email: nathan.a-contact.u9dcm@slmail.me
Requires-Python: >=3.11,<4.0
Classifier: Programming Language :: Python :: 3
Classifier: Programming Language :: Python :: 3.11
Requires-Dist: beautifulsoup4 (>=4.12.3,<5.0.0)
Requires-Dist: uuid (>=1.30,<2.0)
Project-URL: Repository, https://git.inpt.fr/net7/jupytorg
